{
  "url": "https://wow.xxx",
  "finalUrl": "https://www.wow.xxx/",
  "status": 200,
  "statusText": "",
  "requestHeaders": {
    "accept-language": "en-US,en;q=0.9",
    "upgrade-insecure-requests": "1",
    "user-agent": "Mozilla/5.0 (Linux; Android 11; Pixel 5) AppleWebKit/537.36 (KHTML, like Gecko) Chrome/99.0.4812.0 Mobile Safari/537.36",
    ":authority": "www.wow.xxx",
    ":method": "GET",
    ":path": "/",
    ":scheme": "https",
    "accept": "text/html,application/xhtml+xml,application/xml;q=0.9,image/avif,image/webp,image/apng,*/*;q=0.8,application/signed-exchange;v=b3;q=0.7",
    "accept-encoding": "gzip, deflate, br, zstd",
    "priority": "u=0, i",
    "sec-fetch-dest": "document",
    "sec-fetch-mode": "navigate",
    "sec-fetch-site": "none",
    "sec-fetch-user": "?1"
  },
  "responseHeaders": {
    "alt-svc": "h3=\":443\"; ma=86400",
    "cache-control": "no-store, no-cache, must-revalidate",
    "cf-cache-status": "DYNAMIC",
    "cf-ray": "a00362d2ef625aaf-VIE",
    "content-encoding": "zstd",
    "content-type": "text/html; charset=utf-8",
    "date": "Sat, 23 May 2026 10:30:34 GMT",
    "expires": "Thu, 19 Nov 1981 08:52:00 GMT",
    "nel": "{\"report_to\":\"cf-nel\",\"success_fraction\":0.0,\"max_age\":604800}",
    "pragma": "no-cache",
    "priority": "u=0,i",
    "report-to": "{\"group\":\"cf-nel\",\"max_age\":604800,\"endpoints\":[{\"url\":\"https://a.nel.cloudflare.com/report/v4?s=fRjD45G9fpxXMCXk59MgQrSSd%2FFjob3kOCkpogD%2BrZcToYMXidkRXzmgKQnlhXfJSplc6ex1frMBwP5zQJMu3S9E4RnZP09YyJwinKA9RvTCnVKAoqDWNCB2jzjhPqanU7Km8grSP7lmZA%3D%3D\"}]}",
    "server": "cloudflare",
    "server-timing": "cfExtPri",
    "set-cookie": "PHPSESSID=4gl63b28orm09ao2kvh3agc4jc; path=/; domain=.wow.xxx; SameSite=Lax\ncampaign_data=MHxub3wwfDB8bm8%3D; expires=Tue, 19-Jan-2038 03:14:07 GMT; Max-Age=367951413; path=/\nkt_ips=2001%3A629%3A9400%3A1000%3A1%3Ac7d5%3A163a%3A600c; expires=Sun, 24-May-2026 10:30:34 GMT; Max-Age=86400; path=/; domain=.wow.xxx; SameSite=Lax",
    "vary": "Accept-Encoding"
  },
  "redirectChain": [
    {
      "url": "https://wow.xxx/",
      "method": "GET",
      "status": 301,
      "responseHeaders": {
        "alt-svc": "h3=\":443\"; ma=86400",
        "cf-cache-status": "DYNAMIC",
        "cf-ray": "a00362d26f535aaf-VIE",
        "content-type": "text/html; charset=iso-8859-1",
        "date": "Sat, 23 May 2026 10:30:34 GMT",
        "location": "https://www.wow.xxx/",
        "nel": "{\"report_to\":\"cf-nel\",\"success_fraction\":0.0,\"max_age\":604800}",
        "priority": "u=0,i",
        "report-to": "{\"group\":\"cf-nel\",\"max_age\":604800,\"endpoints\":[{\"url\":\"https://a.nel.cloudflare.com/report/v4?s=fq529Pyynmv4igs6PrZ71jz6QUTvvyU0oY6NmFTsEPcmlTby5gDELRcmicq8kzuBAfV%2FLXQ%2BeEPeBlgYU%2FhaQFO4WiziuFTN9u%2Fg6vNAkcK5lyw2TsYc3Ac3s1V7YCOcInJHoUJF\"}]}",
        "server": "cloudflare",
        "server-timing": "cfExtPri"
      }
    }
  ],
  "timestamp": "2026-05-23T10:30:50.087Z"
}