[
  {
    "frameId": "000",
    "url": "https://www.carwale.com/",
    "name": null,
    "isMainFrame": true,
    "adFrameStatus": {
      "adFrameType": "none"
    },
    "iframes": [
      {
        "childFrameId": null,
        "id": "google_ads_iframe_/1017752/Carwale_Mobile_Homepage_FirstSlot_320x150_0",
        "name": "google_ads_iframe_/1017752/Carwale_Mobile_Homepage_FirstSlot_320x150_0",
        "title": "3rd party ad content",
        "width": "300",
        "height": "250",
        "scrolling": "no",
        "marginwidth": "0",
        "marginheight": "0",
        "frameborder": "0",
        "aria-label": "Advertisement",
        "tabindex": "0",
        "allow": "private-state-token-redemption;attribution-reporting",
        "data-load-complete": "true",
        "data-google-container-id": "1",
        "style": "border: 0px; vertical-align: bottom;"
      },
      {
        "childFrameId": "002",
        "name": "googlefcPresent",
        "style": "display: none; width: 0px; height: 0px; border-width: medium; border-style: none; border-color: currentcolor; border-image: initial; z-index: -1000; left: -1000px; top: -1000px;"
      },
      {
        "childFrameId": "003",
        "name": "__tcfapiLocator",
        "src": "about:blank",
        "style": "display: none; width: 0px; height: 0px; border-width: medium; border-style: none; border-color: currentcolor; border-image: initial; z-index: -1000; left: -1000px; top: -1000px;"
      },
      {
        "childFrameId": "004",
        "name": "googlefcInactive",
        "src": "about:blank",
        "style": "display: none; width: 0px; height: 0px; border-width: medium; border-style: none; border-color: currentcolor; border-image: initial; z-index: -1000; left: -1000px; top: -1000px;"
      },
      {
        "childFrameId": "005",
        "name": "googlefcLoaded",
        "src": "about:blank",
        "style": "display: none; width: 0px; height: 0px; border-width: medium; border-style: none; border-color: currentcolor; border-image: initial; z-index: -1000; left: -1000px; top: -1000px;"
      },
      {
        "childFrameId": null,
        "name": "google_ads_top_frame",
        "id": "google_ads_top_frame",
        "style": "display: none; position: fixed; left: -999px; top: -999px; width: 0px; height: 0px;"
      },
      {
        "childFrameId": "001",
        "id": "ce_proto_iframe",
        "title": "CrazyEgg Tracking iframe",
        "aria-hidden": "true",
        "style": "display: none;"
      }
    ]
  },
  {
    "frameId": "001",
    "url": "about:blank",
    "name": "ce_proto_iframe",
    "isMainFrame": false,
    "adFrameStatus": {
      "adFrameType": "none",
      "explanations": []
    },
    "iframes": []
  },
  {
    "frameId": "002",
    "url": "about:blank",
    "name": "googlefcPresent",
    "isMainFrame": false,
    "adFrameStatus": {
      "adFrameType": "root",
      "explanations": [
        "CreatedByAdScript"
      ]
    },
    "iframes": []
  },
  {
    "frameId": "003",
    "url": "about:blank",
    "name": "__tcfapiLocator",
    "isMainFrame": false,
    "adFrameStatus": {
      "adFrameType": "root",
      "explanations": [
        "CreatedByAdScript"
      ]
    },
    "iframes": []
  },
  {
    "frameId": "004",
    "url": "about:blank",
    "name": "googlefcInactive",
    "isMainFrame": false,
    "adFrameStatus": {
      "adFrameType": "root",
      "explanations": [
        "CreatedByAdScript"
      ]
    },
    "iframes": []
  },
  {
    "frameId": "005",
    "url": "about:blank",
    "name": "googlefcLoaded",
    "isMainFrame": false,
    "adFrameStatus": {
      "adFrameType": "root",
      "explanations": [
        "CreatedByAdScript"
      ]
    },
    "iframes": []
  }
]