{
  "url": "https://binance.com",
  "finalUrl": "https://www.binance.com/",
  "status": 202,
  "statusText": "",
  "requestHeaders": {
    "accept-language": "en-US,en;q=0.9",
    "upgrade-insecure-requests": "1",
    "user-agent": "Mozilla/5.0 (Linux; Android 11; Pixel 5) AppleWebKit/537.36 (KHTML, like Gecko) Chrome/99.0.4812.0 Mobile Safari/537.36",
    ":authority": "www.binance.com",
    ":method": "GET",
    ":path": "/",
    ":scheme": "https",
    "accept": "text/html,application/xhtml+xml,application/xml;q=0.9,image/avif,image/webp,image/apng,*/*;q=0.8,application/signed-exchange;v=b3;q=0.7",
    "accept-encoding": "gzip, deflate, br, zstd",
    "priority": "u=0, i",
    "sec-fetch-dest": "document",
    "sec-fetch-mode": "navigate",
    "sec-fetch-site": "none",
    "sec-fetch-user": "?1"
  },
  "responseHeaders": {
    "access-control-allow-methods": "OPTIONS,GET,POST",
    "access-control-allow-origin": "*",
    "access-control-expose-headers": "x-amzn-waf-action",
    "access-control-max-age": "86400",
    "cache-control": "no-store, max-age=0",
    "content-length": "2035",
    "content-type": "text/html; charset=UTF-8",
    "date": "Sat, 23 May 2026 10:39:35 GMT",
    "server": "CloudFront",
    "via": "1.1 f92dcb6dcfa9ba3e4a181203f37934de.cloudfront.net (CloudFront)",
    "x-amz-cf-id": "DTFiC9g79G6CHgCY4biB2Eh1iKAdUrh6dArAp7-LWsl0PsaZvzqVcQ==",
    "x-amz-cf-pop": "VIE50-P4",
    "x-amzn-waf-action": "challenge",
    "x-cache": "Error from cloudfront"
  },
  "redirectChain": [
    {
      "url": "https://binance.com/",
      "method": "GET",
      "status": 301,
      "responseHeaders": {
        "content-length": "162",
        "content-type": "text/html",
        "date": "Sat, 23 May 2026 10:39:34 GMT",
        "location": "https://www.binance.com/",
        "referrer-policy": "origin-when-cross-origin",
        "strict-transport-security": "max-age=31536000; includeSubdomains",
        "x-content-type-options": "nosniff",
        "x-frame-options": "SAMEORIGIN"
      }
    }
  ],
  "timestamp": "2026-05-23T10:39:52.247Z"
}