{
  "url": "https://bulbagarden.net",
  "finalUrl": "https://bulbagarden.net/home/",
  "status": 200,
  "statusText": "",
  "requestHeaders": {
    "accept-language": "en-US,en;q=0.9",
    "upgrade-insecure-requests": "1",
    "user-agent": "Mozilla/5.0 (Linux; Android 11; Pixel 5) AppleWebKit/537.36 (KHTML, like Gecko) Chrome/99.0.4812.0 Mobile Safari/537.36",
    ":authority": "bulbagarden.net",
    ":method": "GET",
    ":path": "/home/",
    ":scheme": "https",
    "accept": "text/html,application/xhtml+xml,application/xml;q=0.9,image/avif,image/webp,image/apng,*/*;q=0.8,application/signed-exchange;v=b3;q=0.7",
    "accept-encoding": "gzip, deflate, br, zstd",
    "priority": "u=0, i",
    "sec-fetch-dest": "document",
    "sec-fetch-mode": "navigate",
    "sec-fetch-site": "none",
    "sec-fetch-user": "?1"
  },
  "responseHeaders": {
    "alt-svc": "h3=\":443\"; ma=86400",
    "cache-control": "private, no-cache, max-age=0",
    "cf-cache-status": "DYNAMIC",
    "cf-ray": "a0038a4b193dc2b6-VIE",
    "content-encoding": "br",
    "content-type": "text/html; charset=utf-8",
    "date": "Sat, 23 May 2026 10:57:31 GMT",
    "expires": "Thu, 19 Nov 1981 08:52:00 GMT",
    "last-modified": "Sat, 23 May 2026 10:57:31 GMT",
    "link": "</js/xf/preamble.min.js?_v=65221cd2>;as=script;rel=preload,</css.php?css=public%3Anormalize.css%2Cpublic%3Afa.css%2Cpublic%3Acore.less%2Cpublic%3Aapp.less&s=62&l=1&d=1779481604&k=4679676895d9f8445592cca071342dfcd46f8a53>;as=style;rel=preload,</js/8wayrun/porta/portal.min.js?_v=65221cd2>;as=script;rel=preload;fetchpriority=low,</js/vendor/vendor-compiled.js?_v=65221cd2>;as=script;rel=preload;fetchpriority=low,</js/xf/core-compiled.js?_v=65221cd2>;as=script;rel=preload;fetchpriority=low,</js/xf/carousel-compiled.js?_v=65221cd2>;as=script;rel=preload;fetchpriority=low,</js/xf/carousel.min.js?_v=65221cd2>;as=script;rel=preload;fetchpriority=low,</css.php?css=public%3AEWRporta.less%2Cpublic%3AEWRporta_articles.less%2Cpublic%3Acarousel.less%2Cpublic%3Amessage.less%2Cpublic%3Anf_discord_widget_online_count.less%2Cpublic%3Anotices.less%2Cpublic%3Aozzmodz_badges.less%2Cpublic%3Ashare_controls.less%2Cpublic%3Axb.less%2Cpublic%3Aextra.less&s=62&l=1&d=1779481604&k=056e665ec504d55c5e2afbebcac8987348584698>;as=style;rel=preload;fetchpriority=low",
    "nel": "{\"report_to\":\"cf-nel\",\"success_fraction\":0.0,\"max_age\":604800}",
    "permissions-policy": "accelerometer=(), camera=(), geolocation=(), gyroscope=(), magnetometer=(), microphone=(), payment=(), usb=()",
    "priority": "u=0,i",
    "referrer-policy": "strict-origin-when-cross-origin",
    "report-to": "{\"group\":\"cf-nel\",\"max_age\":604800,\"endpoints\":[{\"url\":\"https://a.nel.cloudflare.com/report/v4?s=SgIGF5ZlGB1CCPQsxj6Zri7Vth5bzg9kDoHlP3Yf6Y1CM3p3pENl2IV%2FWhIZstKLi7tjx0IIT6rXrZw6IhaW0BL8L08iqc08snEiRFEfGv0r8MtsJIdpgDuj0qAwoPeF%2Bwr4uB6zj4o2WOo0%2BA%3D%3D\"}]}",
    "server": "cloudflare",
    "server-timing": "cfExtPri",
    "set-cookie": "xf_csrf=r0NVR97sJqpsvR20; path=/; domain=.bulbagarden.net; secure",
    "strict-transport-security": "max-age=31536000; includeSubDomains",
    "vary": "Accept-Encoding",
    "x-content-type-options": "nosniff",
    "x-frame-options": "SAMEORIGIN"
  },
  "redirectChain": [
    {
      "url": "https://bulbagarden.net/",
      "method": "GET",
      "status": 301,
      "responseHeaders": {
        "alt-svc": "h3=\":443\"; ma=86400",
        "cache-control": "private, no-cache, max-age=0",
        "cf-cache-status": "DYNAMIC",
        "cf-ray": "a0038a4938e6c2b6-VIE",
        "content-type": "text/html; charset=utf-8",
        "date": "Sat, 23 May 2026 10:57:31 GMT",
        "expires": "Thu, 19 Nov 1981 08:52:00 GMT",
        "last-modified": "Sat, 23 May 2026 10:57:31 GMT",
        "link": "</css.php?css=public%3Aextra.less&s=62&l=1&d=1779481604&k=78dcd5ff81cd00b6b7af54121a091f0895793cbc>;as=style;rel=preload;fetchpriority=low",
        "location": "https://bulbagarden.net/home/",
        "nel": "{\"report_to\":\"cf-nel\",\"success_fraction\":0.0,\"max_age\":604800}",
        "permissions-policy": "accelerometer=(), camera=(), geolocation=(), gyroscope=(), magnetometer=(), microphone=(), payment=(), usb=()",
        "priority": "u=0,i",
        "referrer-policy": "strict-origin-when-cross-origin",
        "report-to": "{\"group\":\"cf-nel\",\"max_age\":604800,\"endpoints\":[{\"url\":\"https://a.nel.cloudflare.com/report/v4?s=E%2BQJYk0dSsd8UPq47fg2FsVfZHMyznJEgaWkheU1MdBKCgfWlGW8GzjprY8FCJK5x1%2BbwE%2FH8gfgl02Z0LvmO%2BwghDzTEPVHujg%2BtHe9AZuy%2B0WrdltemSTPkRJvveXF1kluFPD4ieeIZUTKcw%3D%3D\"}]}",
        "server": "cloudflare",
        "server-timing": "cfExtPri",
        "strict-transport-security": "max-age=31536000; includeSubDomains",
        "x-content-type-options": "nosniff",
        "x-frame-options": "SAMEORIGIN"
      }
    }
  ],
  "timestamp": "2026-05-23T10:57:59.687Z"
}