{
  "url": "https://arsnouveau.wiki",
  "finalUrl": "https://www.arsnouveau.wiki/",
  "status": 200,
  "statusText": "",
  "requestHeaders": {
    "accept-language": "en-US,en;q=0.9",
    "upgrade-insecure-requests": "1",
    "user-agent": "Mozilla/5.0 (Linux; Android 11; Pixel 5) AppleWebKit/537.36 (KHTML, like Gecko) Chrome/99.0.4812.0 Mobile Safari/537.36",
    ":authority": "www.arsnouveau.wiki",
    ":method": "GET",
    ":path": "/",
    ":scheme": "https",
    "accept": "text/html,application/xhtml+xml,application/xml;q=0.9,image/avif,image/webp,image/apng,*/*;q=0.8,application/signed-exchange;v=b3;q=0.7",
    "accept-encoding": "gzip, deflate, br, zstd",
    "priority": "u=0, i",
    "sec-fetch-dest": "document",
    "sec-fetch-mode": "navigate",
    "sec-fetch-site": "none",
    "sec-fetch-user": "?1"
  },
  "responseHeaders": {
    "age": "0",
    "cache-control": "public, max-age=0, must-revalidate",
    "content-encoding": "br",
    "content-type": "text/html",
    "date": "Sat, 23 May 2026 14:02:57 GMT",
    "etag": "W/\"8hwdu\"",
    "link": "<./_app/immutable/assets/0.8518d6bb.css>; rel=\"preload\";as=\"style\"; nopush, <./_app/immutable/assets/AddonInformation.95c934ca.css>; rel=\"preload\";as=\"style\"; nopush, <./_app/immutable/entry/start.7bfe6ca1.js>; rel=\"modulepreload\"; nopush, <./_app/immutable/chunks/index.3480645f.js>; rel=\"modulepreload\"; nopush, <./_app/immutable/chunks/singletons.50838299.js>; rel=\"modulepreload\"; nopush, <./_app/immutable/chunks/index.bfd86403.js>; rel=\"modulepreload\"; nopush, <./_app/immutable/entry/app.99069216.js>; rel=\"modulepreload\"; nopush, <./_app/immutable/nodes/0.4fff2b3b.js>; rel=\"modulepreload\"; nopush, <./_app/immutable/chunks/textures.a507d943.js>; rel=\"modulepreload\"; nopush, <./_app/immutable/chunks/AddonInformation.79ada6c3.js>; rel=\"modulepreload\"; nopush, <./_app/immutable/chunks/modInformations.e4a943eb.js>; rel=\"modulepreload\"; nopush, <./_app/immutable/chunks/uiState.5cbf0a1c.js>; rel=\"modulepreload\"; nopush, <./_app/immutable/nodes/2.30fe160d.js>; rel=\"modulepreload\"; nopush",
    "server": "Vercel",
    "strict-transport-security": "max-age=63072000",
    "x-sveltekit-page": "true",
    "x-vercel-cache": "MISS",
    "x-vercel-id": "fra1::iad1::gvkck-1779544977092-601b39d52ef7"
  },
  "redirectChain": [
    {
      "url": "https://arsnouveau.wiki/",
      "method": "GET",
      "status": 308,
      "responseHeaders": {
        "cache-control": "public, max-age=0, must-revalidate",
        "content-type": "text/html",
        "date": "Sat, 23 May 2026 14:02:57 GMT",
        "location": "https://www.arsnouveau.wiki/",
        "refresh": "0;url=https://www.arsnouveau.wiki/",
        "server": "Vercel",
        "strict-transport-security": "max-age=63072000",
        "x-vercel-id": "fra1::nvmp7-1779544977008-d7b5f3f13fab"
      }
    }
  ],
  "timestamp": "2026-05-23T14:03:07.355Z"
}