[
  {
    "frameId": "000",
    "url": "https://pcbolsa.com/Creditos?Resul=5",
    "name": null,
    "isMainFrame": true,
    "adFrameStatus": {
      "adFrameType": "none"
    },
    "iframes": [
      {
        "childFrameId": "001",
        "src": "https://accounts.google.com/gsi/button?type=standard&shape=rectangular&theme=filled_blue&text=signin_with&size=large&logo_alignment=left&is_fedcm_supported=false&client_id=855119026940-jf9ljr6bjedh63645heeiv61jm8gcrn4.apps.googleusercontent.com&iframe_id=gsi_451559_455485&cas=HDz7E8yfPsSOuGUQc1B46jaUgEP9R9H7rM41PQPDRQs",
        "class": "L5Fo6c-PQbLGe",
        "allow": "identity-credentials-get",
        "id": "gsi_451559_455485",
        "title": "Button „Über Google anmelden“",
        "style": "display: block; position: relative; top: 0px; left: 0px; height: 0px; width: 0px; border: 0px;"
      },
      {
        "childFrameId": "002",
        "name": "oauth2relay414317378",
        "id": "oauth2relay414317378",
        "src": "https://accounts.google.com/o/oauth2/postmessageRelay?parent=https%3A%2F%2Fpcbolsa.com&jsh=m%3B%2F_%2Fscs%2Fabc-static%2F_%2Fjs%2Fk%3Dgapi.lb.en.ch0Jz-JlMrQ.O%2Fd%3D1%2Frs%3DAHpOoo_YD4KoV8fTh_kLhktsiThAm3yJ5A%2Fm%3D__features__#rpctoken=292743380&forcesecure=1",
        "tabindex": "-1",
        "aria-hidden": "true",
        "style": "width: 1px; height: 1px; position: absolute; top: -100px;"
      }
    ]
  },
  {
    "frameId": "001",
    "url": "https://accounts.google.com/gsi/button?type=standard&shape=rectangular&theme=filled_blue&text=signin_with&size=large&logo_alignment=left&is_fedcm_supported=false&client_id=855119026940-jf9ljr6bjedh63645heeiv61jm8gcrn4.apps.googleusercontent.com&iframe_id=gsi_451559_455485&cas=HDz7E8yfPsSOuGUQc1B46jaUgEP9R9H7rM41PQPDRQs",
    "name": null,
    "isMainFrame": false,
    "adFrameStatus": null,
    "iframes": []
  },
  {
    "frameId": "002",
    "url": "https://accounts.google.com/o/oauth2/postmessageRelay?parent=https%3A%2F%2Fpcbolsa.com&jsh=m%3B%2F_%2Fscs%2Fabc-static%2F_%2Fjs%2Fk%3Dgapi.lb.en.ch0Jz-JlMrQ.O%2Fd%3D1%2Frs%3DAHpOoo_YD4KoV8fTh_kLhktsiThAm3yJ5A%2Fm%3D__features__#rpctoken=292743380&forcesecure=1",
    "name": "oauth2relay414317378",
    "isMainFrame": false,
    "adFrameStatus": null,
    "iframes": []
  }
]