[
  {
    "frameId": "000",
    "url": "https://kinoger.fun/",
    "name": null,
    "isMainFrame": true,
    "adFrameStatus": {
      "adFrameType": "none"
    },
    "iframes": [
      {
        "childFrameId": "001",
        "height": "1",
        "width": "1",
        "style": "position: absolute; top: 0px; left: 0px; border-width: medium; border-style: none; border-color: currentcolor; border-image: initial; visibility: hidden;"
      },
      {
        "childFrameId": "002",
        "id": "container-7946681438002dc2fe18521a43bb547263437",
        "class": "container-7946681438002dc2fe18521a43bb547263437",
        "width": "520px",
        "height": "280px",
        "style": "display: block; border-width: medium; border-style: none; border-color: currentcolor; border-image: initial; position: fixed; z-index: 2147483647; max-width: 90%; margin: auto; width: 520px; height: 280px; inset: auto 0px 10px;"
      }
    ]
  },
  {
    "frameId": "001",
    "url": "about:blank",
    "name": null,
    "isMainFrame": false,
    "adFrameStatus": {
      "adFrameType": "none",
      "explanations": []
    },
    "iframes": []
  },
  {
    "frameId": "002",
    "url": "about:blank",
    "name": "container-7946681438002dc2fe18521a43bb547263437",
    "isMainFrame": false,
    "adFrameStatus": {
      "adFrameType": "none",
      "explanations": []
    },
    "iframes": []
  }
]