{
  "url": "https://manhwaread.com",
  "finalUrl": "https://manhwaread.com/",
  "status": 200,
  "statusText": "",
  "requestHeaders": {
    "accept-language": "en-US,en;q=0.9",
    "upgrade-insecure-requests": "1",
    "user-agent": "Mozilla/5.0 (Linux; Android 11; Pixel 5) AppleWebKit/537.36 (KHTML, like Gecko) Chrome/99.0.4812.0 Mobile Safari/537.36",
    ":authority": "manhwaread.com",
    ":method": "GET",
    ":path": "/",
    ":scheme": "https",
    "accept": "text/html,application/xhtml+xml,application/xml;q=0.9,image/avif,image/webp,image/apng,*/*;q=0.8,application/signed-exchange;v=b3;q=0.7",
    "accept-encoding": "gzip, deflate, br, zstd",
    "priority": "u=0, i",
    "sec-fetch-dest": "document",
    "sec-fetch-mode": "navigate",
    "sec-fetch-site": "none",
    "sec-fetch-user": "?1"
  },
  "responseHeaders": {
    "age": "85336",
    "alt-svc": "h3=\":443\"; ma=86400",
    "cf-cache-status": "HIT",
    "cf-ray": "a0037a87bc6a3264-VIE",
    "content-encoding": "zstd",
    "content-type": "text/html; charset=UTF-8",
    "date": "Sat, 23 May 2026 10:46:45 GMT",
    "last-modified": "Fri, 22 May 2026 11:04:28 GMT",
    "nel": "{\"report_to\":\"cf-nel\",\"success_fraction\":0.0,\"max_age\":604800}",
    "permissions-policy": "fullscreen=(self)",
    "priority": "u=0,i",
    "referrer-policy": "strict-origin-when-cross-origin",
    "report-to": "{\"group\":\"cf-nel\",\"max_age\":604800,\"endpoints\":[{\"url\":\"https://a.nel.cloudflare.com/report/v4?s=a0OUbtTwFbW0cJIvpGaSGM4uvae7P9ZD2nffSFli4knBTI9hYuJZuN7HolZEXoSUAiHmZ6n6JSAOLxFGR2Qzdh2yxODNJ%2FVDp1oBv%2BOFA415yL5%2Bu%2F2ZLi90SaeZjMu7kntYy%2Bc7e2OQiEVfSw%3D%3D\"}]}",
    "server": "cloudflare",
    "server-timing": "cfCacheStatus;desc=\"HIT\"\ncfEdge;dur=7,cfOrigin;dur=0\ncfExtPri",
    "speculation-rules": "\"/cdn-cgi/speculation\"",
    "strict-transport-security": "max-age=15768000; includeSubDomains\nmax-age=31536000; includeSubDomains\nmax-age=31536000; includeSubDomains; preload",
    "vary": "accept-encoding",
    "x-content-type-options": "nosniff\nnosniff",
    "x-frame-options": "SAMEORIGIN\nSAMEORIGIN",
    "x-powered-by": "PleskLin",
    "x-rocket-nginx-serving-static": "MISS",
    "x-xss-protection": "1; mode=block\n1; mode=block"
  },
  "redirectChain": [],
  "timestamp": "2026-05-23T10:46:59.525Z"
}