{
  "url": "https://parivahan.gov.in",
  "finalUrl": "https://parivahan.gov.in/",
  "status": 200,
  "statusText": "OK",
  "requestHeaders": {
    "accept-language": "en-US,en;q=0.9",
    "upgrade-insecure-requests": "1",
    "user-agent": "Mozilla/5.0 (Linux; Android 11; Pixel 5) AppleWebKit/537.36 (KHTML, like Gecko) Chrome/99.0.4812.0 Mobile Safari/537.36",
    "accept": "text/html,application/xhtml+xml,application/xml;q=0.9,image/avif,image/webp,image/apng,*/*;q=0.8,application/signed-exchange;v=b3;q=0.7",
    "accept-encoding": "gzip, deflate, br, zstd",
    "connection": "keep-alive",
    "host": "parivahan.gov.in",
    "sec-fetch-dest": "document",
    "sec-fetch-mode": "navigate",
    "sec-fetch-site": "none",
    "sec-fetch-user": "?1"
  },
  "responseHeaders": {
    "cache-control": "no-store, no-cache, must-revalidate, max-age=0",
    "connection": "keep-alive",
    "content-length": "293685",
    "content-security-policy": "report-uri /report-csp-violation\ndefault-src 'self'; script-src 'self'; style-src 'self'; img-src 'self';",
    "content-type": "text/html; charset=UTF-8",
    "content-language": "en",
    "date": "Sat, 23 May 2026 10:17:31 GMT",
    "expires": "Sun, 19 Nov 1978 05:00:00 GMT",
    "from-origin": "same",
    "pragma": "no-cache",
    "referrer-policy": "strict-origin-when-cross-origin",
    "strict-transport-security": "max-age=31536000; includeSubDomains; preload",
    "x-content-security-policy": "report-uri /report-csp-violation",
    "x-content-type-options": "nosniff",
    "x-drupal-cache": "UNCACHEABLE (response policy)",
    "x-drupal-dynamic-cache": "UNCACHEABLE (response policy)",
    "x-frame-options": "SAMEORIGIN",
    "x-webkit-csp": "report-uri /report-csp-violation",
    "x-xss-protection": "1; mode=block"
  },
  "redirectChain": [],
  "timestamp": "2026-05-23T10:17:46.281Z"
}