{
  "url": "https://vicecityspin.net",
  "finalUrl": "https://www.vicecityspin.net/?comLogin=1",
  "status": 200,
  "statusText": "",
  "requestHeaders": {
    "accept-language": "en-US,en;q=0.9",
    "upgrade-insecure-requests": "1",
    "user-agent": "Mozilla/5.0 (Linux; Android 11; Pixel 5) AppleWebKit/537.36 (KHTML, like Gecko) Chrome/99.0.4812.0 Mobile Safari/537.36",
    ":authority": "www.vicecityspin.net",
    ":method": "GET",
    ":path": "/?comLogin=1",
    ":scheme": "https",
    "accept": "text/html,application/xhtml+xml,application/xml;q=0.9,image/avif,image/webp,image/apng,*/*;q=0.8,application/signed-exchange;v=b3;q=0.7",
    "accept-encoding": "gzip, deflate, br, zstd",
    "cookie": "PHPSESSID=g-6de4c71ec57b40cada33008f8acbf420; platformBehaviour=android; langId=8; UIN=14863023426a11b8e81b1511.58428876; domain_visited=1; ALSD_CHECK=1",
    "priority": "u=0, i",
    "sec-fetch-dest": "document",
    "sec-fetch-mode": "navigate",
    "sec-fetch-site": "none",
    "sec-fetch-user": "?1"
  },
  "responseHeaders": {
    "access-control-allow-headers": "origin, x-requested-with, content-type",
    "access-control-allow-methods": "PUT, GET, POST, DELETE, OPTIONS",
    "alt-svc": "h3=\":443\"; ma=86400",
    "cache-control": "no-store, no-cache, must-revalidate",
    "cf-cache-status": "DYNAMIC",
    "cf-ray": "a004bb4c49f8d8dc-VIE",
    "content-encoding": "zstd",
    "content-type": "text/html; charset=UTF-8",
    "date": "Sat, 23 May 2026 14:25:45 GMT",
    "expires": "Thu, 19 Nov 1981 08:52:00 GMT",
    "nel": "{\"report_to\":\"cf-nel\",\"success_fraction\":0.0,\"max_age\":604800}",
    "pragma": "no-cache",
    "priority": "u=0,i",
    "report-to": "{\"group\":\"cf-nel\",\"max_age\":604800,\"endpoints\":[{\"url\":\"https://a.nel.cloudflare.com/report/v4?s=YdJYo12Si%2BxIgeipsAlYDeL03FAqW8vcB%2Bt4Zc3IccTO6g5JuWt%2FJjnR9HNLAPlsjuFEdu3voP7jdgeVfy2Nq%2B0hiFvnJch99DvzlDVi4dxj8qUhu%2Fn%2FyXuReGxVL2cCxayjzyXPKjuPqYmlwPNMM59hXg%3D%3D\"}]}",
    "server": "cloudflare",
    "server-timing": "cfExtPri",
    "strict-transport-security": "max-age=31536000; includeSubDomains; preload",
    "vary": "Accept-Encoding",
    "x-content-type-options": "nosniff",
    "x-xss-protection": "1; mode=block"
  },
  "redirectChain": [
    {
      "url": "https://vicecityspin.net/",
      "method": "GET",
      "status": 301,
      "responseHeaders": {
        "access-control-allow-headers": "origin, x-requested-with, content-type",
        "access-control-allow-methods": "PUT, GET, POST, DELETE, OPTIONS",
        "alt-svc": "h3=\":443\"; ma=86400",
        "cf-cache-status": "DYNAMIC",
        "cf-ray": "a004bb487964d8dc-VIE",
        "content-type": "text/html",
        "date": "Sat, 23 May 2026 14:25:43 GMT",
        "location": "https://www.vicecityspin.net/",
        "nel": "{\"report_to\":\"cf-nel\",\"success_fraction\":0.0,\"max_age\":604800}",
        "priority": "u=0,i",
        "report-to": "{\"group\":\"cf-nel\",\"max_age\":604800,\"endpoints\":[{\"url\":\"https://a.nel.cloudflare.com/report/v4?s=Di5XZB4ZEsrGXVXhCNlF05GV94qJ27aYA4YOIPPn6DG9O9ydMlH0nf8CrIl4vduiiSxnKH7lfU14dJYid2lh0qFeT4QD9tBVlwrEmXiwKa4kVuax4jd56Z%2BlLmaT%2Be0RFmr9XPJQ0GBHHuOZo1iQ\"}]}",
        "server": "cloudflare",
        "server-timing": "cfExtPri",
        "strict-transport-security": "max-age=31536000; includeSubDomains; preload",
        "x-content-type-options": "nosniff",
        "x-xss-protection": "1; mode=block"
      }
    },
    {
      "url": "https://www.vicecityspin.net/",
      "method": "GET",
      "status": 302,
      "responseHeaders": {
        "access-control-allow-headers": "origin, x-requested-with, content-type",
        "access-control-allow-methods": "PUT, GET, POST, DELETE, OPTIONS",
        "alt-svc": "h3=\":443\"; ma=86400",
        "cache-control": "no-store, no-cache, must-revalidate\nno-cache, private",
        "cf-cache-status": "DYNAMIC",
        "cf-ray": "a004bb498bddd8dc-VIE",
        "content-type": "text/html; charset=utf-8",
        "date": "Sat, 23 May 2026 14:25:44 GMT",
        "expires": "Thu, 19 Nov 1981 08:52:00 GMT",
        "location": "https://login5.vicecityspin300.com?comLogin=1&o_url=https%253A%252F%252Fwww.vicecityspin.net%252F&com_set%5BVIP%5D=0",
        "nel": "{\"report_to\":\"cf-nel\",\"success_fraction\":0.0,\"max_age\":604800}",
        "pragma": "no-cache",
        "priority": "u=0,i",
        "report-to": "{\"group\":\"cf-nel\",\"max_age\":604800,\"endpoints\":[{\"url\":\"https://a.nel.cloudflare.com/report/v4?s=icTQ1ra%2F%2FJB1NPr8iISG1Wz%2FJyR7EI8BdXBLEBYUc0lT3rN3zKXtMYM3TrOhw9QqtzR3e%2FPSFuLcV2yrTKAHM9NJ5hNb9BL7nc12UIMB7xWEWfMiVSudyWd5svJNR3i9mGaFW46AtnQcaW7dQqGVF1n5Gw%3D%3D\"}]}",
        "server": "cloudflare",
        "server-timing": "cfExtPri",
        "set-cookie": "PHPSESSID=g-6de4c71ec57b40cada33008f8acbf420; expires=Sun, 24-May-2026 02:25:44 GMT; Max-Age=43200; path=/; domain=vicecityspin.net; secure; HttpOnly\nplatformBehaviour=android; path=/; secure; HttpOnly; SameSite=None\nlangId=8; path=/; secure; HttpOnly; SameSite=None\nUIN=14863023426a11b8e81b1511.58428876; expires=Sun, 21-Jun-2026 12:52:24 GMT; Max-Age=2500000; path=/; domain=vicecityspin.net; HttpOnly; SameSite=Lax\nUIN=14863023426a11b8e81b1511.58428876; expires=Sun, 21-Jun-2026 12:52:24 GMT; Max-Age=2500000; path=/; domain=.vicecityspin.net; HttpOnly; SameSite=Lax\ndomain_visited=1; expires=Sun, 24-May-2026 14:25:44 GMT; Max-Age=86400; path=/; domain=vicecityspin.net; HttpOnly; SameSite=Lax\ndomain_visited=1; expires=Sun, 24-May-2026 14:25:44 GMT; Max-Age=86400; path=/; domain=.vicecityspin.net; HttpOnly; SameSite=Lax\nALSD_CHECK=1; expires=Sat, 23-May-2026 15:25:44 GMT; Max-Age=3600; path=/; secure; HttpOnly; SameSite=None",
        "strict-transport-security": "max-age=31536000; includeSubDomains; preload",
        "x-content-type-options": "nosniff",
        "x-xss-protection": "1; mode=block"
      }
    },
    {
      "url": "https://login5.vicecityspin300.com/?comLogin=1&o_url=https%253A%252F%252Fwww.vicecityspin.net%252F&com_set%5BVIP%5D=0",
      "method": "GET",
      "status": 303,
      "responseHeaders": {
        "access-control-allow-headers": "Access-Control-Allow-Headers, Access-Control-Request-Headers, Access-Control-Request-Method, X-Requested-With, Content-Type, Origin, Accept, Authorization, x-xsrf-token",
        "access-control-allow-methods": "GET,HEAD,OPTIONS,POST,PUT",
        "access-control-allow-origin": "*",
        "access-control-max-age": "3600",
        "alt-svc": "h3=\":443\"; ma=86400",
        "cf-cache-status": "DYNAMIC",
        "cf-ray": "a004bb4b49fec289-VIE",
        "content-type": "text/html; charset=UTF-8",
        "date": "Sat, 23 May 2026 14:25:44 GMT",
        "location": "https://www.vicecityspin.net/?comLogin=1",
        "nel": "{\"report_to\":\"cf-nel\",\"success_fraction\":0.0,\"max_age\":604800}",
        "priority": "u=0,i",
        "report-to": "{\"group\":\"cf-nel\",\"max_age\":604800,\"endpoints\":[{\"url\":\"https://a.nel.cloudflare.com/report/v4?s=4%2FZziHPORMSY3mMIZUc38D%2FepY2u5YtYFs4p5chniyvPborwVkfgjS6DdoTPSspdd8bvwGjbc7E6NRBRUkFz1Knxve8m1C%2FTnwRNOGhFHDduViyYsjJrC5xzkimn3dlXKs3m5i57pA%2FPIUR8D3WKuhLQ92oeH41c9Q%3D%3D\"}]}",
        "server": "cloudflare",
        "server-timing": "cfExtPri",
        "set-cookie": "VIP=0; expires=Sun, 23-May-2027 14:25:44 GMT; Max-Age=31536000; path=/; domain=login5.vicecityspin300.com"
      }
    }
  ],
  "timestamp": "2026-05-23T14:25:55.857Z"
}