{
  "url": "https://quizlet.com",
  "finalUrl": "https://quizlet.com/",
  "status": 200,
  "statusText": "",
  "requestHeaders": {
    "accept-language": "en-US,en;q=0.9",
    "upgrade-insecure-requests": "1",
    "user-agent": "Mozilla/5.0 (Linux; Android 11; Pixel 5) AppleWebKit/537.36 (KHTML, like Gecko) Chrome/99.0.4812.0 Mobile Safari/537.36",
    ":authority": "quizlet.com",
    ":method": "GET",
    ":path": "/",
    ":scheme": "https",
    "accept": "text/html,application/xhtml+xml,application/xml;q=0.9,image/avif,image/webp,image/apng,*/*;q=0.8,application/signed-exchange;v=b3;q=0.7",
    "accept-encoding": "gzip, deflate, br, zstd",
    "priority": "u=0, i",
    "sec-fetch-dest": "document",
    "sec-fetch-mode": "navigate",
    "sec-fetch-site": "none",
    "sec-fetch-user": "?1"
  },
  "responseHeaders": {
    "cache-control": "private, no-cache, no-store, max-age=0, must-revalidate",
    "cf-cache-status": "DYNAMIC",
    "cf-ray": "a003514e38b98f2b-VIE",
    "content-encoding": "br",
    "content-type": "text/html; charset=utf-8",
    "date": "Sat, 23 May 2026 10:18:37 GMT",
    "quizlet-action-name": "Homepage/index",
    "quizlet-route-importance": "normal",
    "server": "cloudflare",
    "set-cookie": "qi5=1frucu2kchj90%3AZ3llt9I.VP5lUog5X30O; Max-Age=315360000; Path=/; Expires=Tue, 20 May 2036 10:18:37 GMT; HttpOnly; Secure\nqtkn=AxawBSG9jPhyZwHxwgCc8m; Path=/; Secure\nfs=tfhjb1; Max-Age=315360000; Path=/; Expires=Tue, 20 May 2036 10:18:37 GMT; HttpOnly; Secure\napp_session_id=5b7318d4-ae05-437a-b90b-9ef07a6e8887; Max-Age=1800; Path=/; Expires=Sat, 23 May 2026 10:48:37 GMT; Secure\n_pxhd=35815dd6c3f0be30ceb7b2a4b4ffab0ab8cb4bde1d284c956fa15f12e2ebb1eb:c30237e7-5690-11f1-943c-3c525a4f355c; path=/; SameSite=Lax\n__cf_bm=aMszRa1kTcq.eBYslpR8ScPBtapPmdYEFc3MhH.UY.s-1779531517.1557238-1.0.1.1-cElw_fOUrbB2lKMyclpPOVGsUchE_9Rtg2AJs6QTgUvMdysFY9DqDem7Q5_hCDqaMoDg5pYCPLQN7RfuObnV0UKChnWN32a4BwA7DCCrnYYu0KOz.pxqljMFtxqsV5zo; HttpOnly; SameSite=None; Secure; Path=/; Domain=quizlet.com; Expires=Sat, 23 May 2026 10:48:37 GMT\n_cfuvid=MdorGYYaYu66UkLxccsrwZNuUv.9qTrbVwdvNb75M4I-1779531517.1557238-1.0.1.1-Mq8zcBDG762IbBsds6TAGduEpmfK5FydEqs7ORBL_TA; HttpOnly; SameSite=None; Secure; Path=/; Domain=quizlet.com",
    "vary": "Accept-Encoding",
    "via": "1.1 google"
  },
  "redirectChain": [],
  "timestamp": "2026-05-23T10:19:29.622Z"
}