{
  "url": "https://gosugamers.net",
  "finalUrl": "https://www.gosugamers.net/",
  "status": 200,
  "statusText": "",
  "requestHeaders": {
    "accept-language": "en-US,en;q=0.9",
    "upgrade-insecure-requests": "1",
    "user-agent": "Mozilla/5.0 (Linux; Android 11; Pixel 5) AppleWebKit/537.36 (KHTML, like Gecko) Chrome/99.0.4812.0 Mobile Safari/537.36",
    ":authority": "www.gosugamers.net",
    ":method": "GET",
    ":path": "/",
    ":scheme": "https",
    "accept": "text/html,application/xhtml+xml,application/xml;q=0.9,image/avif,image/webp,image/apng,*/*;q=0.8,application/signed-exchange;v=b3;q=0.7",
    "accept-encoding": "gzip, deflate, br, zstd",
    "priority": "u=0, i",
    "sec-fetch-dest": "document",
    "sec-fetch-mode": "navigate",
    "sec-fetch-site": "none",
    "sec-fetch-user": "?1"
  },
  "responseHeaders": {
    "alt-svc": "h3=\":443\"; ma=86400",
    "cache-control": "private, no-cache, no-store, max-age=0, must-revalidate",
    "cf-cache-status": "DYNAMIC",
    "cf-ray": "a0048c3c1b5d5af4-VIE",
    "content-encoding": "zstd",
    "content-type": "text/html; charset=utf-8",
    "date": "Sat, 23 May 2026 13:53:37 GMT",
    "link": "<https://static.gosugamers.net>; rel=preconnect; crossorigin\n</_next/static/media/48d6c1d8cdabb02e-s.p.woff2>; rel=preload; as=\"font\"; crossorigin=\"\"; type=\"font/woff2\", </_next/static/media/959a5f647d0f9bf4-s.p.woff2>; rel=preload; as=\"font\"; crossorigin=\"\"; type=\"font/woff2\"",
    "nel": "{\"report_to\":\"cf-nel\",\"success_fraction\":0.0,\"max_age\":604800}",
    "permissions-policy": "camera=(), microphone=(), geolocation=(), browsing-topics=()",
    "priority": "u=0,i",
    "referrer-policy": "strict-origin-when-cross-origin",
    "report-to": "{\"group\":\"cf-nel\",\"max_age\":604800,\"endpoints\":[{\"url\":\"https://a.nel.cloudflare.com/report/v4?s=Uz1GgYsz8OXn6Z%2BfbZPg6a1hLuWYmzA7mdw2olLj8qc3foGd81dDuLnyPXRFcKG60YQep0pwRAsUPLTu2FVYHG%2FDG5kNQEgM5vMHg2QLyWKrI5IzPoZtS6fZZOfegR6lqUBqT4nMKCwOZOk5gj40Zg%3D%3D\"}]}",
    "server": "cloudflare",
    "server-timing": "cfCacheStatus;desc=\"DYNAMIC\"\ncfEdge;dur=14,cfOrigin;dur=831\ncfExtPri",
    "set-cookie": "NEXT_LOCALE=en-GB; Path=/; Expires=Sun, 23 May 2027 13:53:37 GMT; Max-Age=31536000; SameSite=lax",
    "speculation-rules": "\"/cdn-cgi/speculation\"",
    "strict-transport-security": "max-age=63072000; includeSubDomains; preload",
    "vary": "RSC, Next-Router-State-Tree, Next-Router-Prefetch, Accept-Encoding",
    "x-content-type-options": "nosniff",
    "x-frame-options": "SAMEORIGIN",
    "x-middleware-rewrite": "/en-GB",
    "x-powered-by": "Next.js"
  },
  "redirectChain": [
    {
      "url": "https://gosugamers.net/",
      "method": "GET",
      "status": 301,
      "responseHeaders": {
        "alt-svc": "h3=\":443\"; ma=86400",
        "cf-ray": "a0048c3bddf45afa-VIE",
        "content-type": "text/html; charset=UTF-8",
        "date": "Sat, 23 May 2026 13:53:36 GMT",
        "location": "https://www.gosugamers.net/",
        "nel": "{\"report_to\":\"cf-nel\",\"success_fraction\":0.0,\"max_age\":604800}",
        "priority": "u=0,i",
        "report-to": "{\"group\":\"cf-nel\",\"max_age\":604800,\"endpoints\":[{\"url\":\"https://a.nel.cloudflare.com/report/v4?s=NxMpg09b8ZyANqVs59%2FTIg9%2FWiyvLQN9gfnAulS79CcPW%2FbpEol9JtmoDuXpMkxV4gha4M%2FUgT3u1Ptizw4wYbvJ64E%2FcIqAXBhcSP5lX2aKsEjWGoApR0yaqd4L%2F9lZEARByyLwWLRi9Txg\"}]}",
        "server": "cloudflare",
        "server-timing": "cfEdge;dur=4,cfOrigin;dur=0\ncfExtPri",
        "speculation-rules": "\"/cdn-cgi/speculation\"",
        "vary": "accept-encoding"
      }
    }
  ],
  "timestamp": "2026-05-23T13:53:48.061Z"
}