{
  "url": "https://pravda.com.ua",
  "finalUrl": "https://www.pravda.com.ua/",
  "status": 200,
  "statusText": "",
  "requestHeaders": {
    "accept-language": "en-US,en;q=0.9",
    "upgrade-insecure-requests": "1",
    "user-agent": "Mozilla/5.0 (Linux; Android 11; Pixel 5) AppleWebKit/537.36 (KHTML, like Gecko) Chrome/99.0.4812.0 Mobile Safari/537.36",
    ":authority": "www.pravda.com.ua",
    ":method": "GET",
    ":path": "/",
    ":scheme": "https",
    "accept": "text/html,application/xhtml+xml,application/xml;q=0.9,image/avif,image/webp,image/apng,*/*;q=0.8,application/signed-exchange;v=b3;q=0.7",
    "accept-encoding": "gzip, deflate, br, zstd",
    "priority": "u=0, i",
    "sec-fetch-dest": "document",
    "sec-fetch-mode": "navigate",
    "sec-fetch-site": "none",
    "sec-fetch-user": "?1"
  },
  "responseHeaders": {
    "age": "19",
    "alt-svc": "h3=\":443\"; ma=86400",
    "cache-control": "max-age=0, must-revalidate, public, s-maxage=270, no-store",
    "cache-status": "hit",
    "cf-cache-status": "HIT",
    "cf-ray": "a00361a85c5bc29b-VIE",
    "content-encoding": "br",
    "content-type": "text/html; charset=utf-8",
    "date": "Sat, 23 May 2026 10:29:46 GMT",
    "last-modified": "Sat, 23 May 2026 10:29:27 GMT",
    "priority": "u=0,i",
    "server": "cloudflare",
    "server-timing": "cfExtPri",
    "vary": "accept-encoding",
    "x-varnish-hash": "GET:www.pravda.com.ua/:mobile"
  },
  "redirectChain": [
    {
      "url": "https://pravda.com.ua/",
      "method": "GET",
      "status": 301,
      "responseHeaders": {
        "alt-svc": "h3=\":443\"; ma=86400",
        "cf-ray": "a00361a81c54c29b-VIE",
        "content-type": "text/html; charset=UTF-8",
        "date": "Sat, 23 May 2026 10:29:46 GMT",
        "location": "https://www.pravda.com.ua/",
        "server": "cloudflare"
      }
    }
  ],
  "timestamp": "2026-05-23T10:30:19.675Z"
}